dv_net_client/__init__.py
dv_net_client/_base_client.py
dv_net_client/async_client.py
dv_net_client/client.py
dv_net_client/dto/__init__.py
dv_net_client/dto/merchant_client.py
dv_net_client/dto/webhook.py
dv_net_client/exceptions.py
dv_net_client/http_client.py
dv_net_client/mappers.py
dv_net_client/utils.py
dv_net_client-1.0.0.dist-info/LICENSE
dv_net_client-1.0.0.dist-info/METADATA
dv_net_client-1.0.0.dist-info/WHEEL
dv_net_client-1.0.0.dist-info/RECORD
