Metadata-Version: 2.1
Name: dv-net-client
Version: 1.0.0
Summary: A convenient way to integrate DV.net to your platform
Home-page: https://docs.dv.net
License: MIT
Keywords: api,client,dv.net,payment,crypto
Author: Kurt Morgan
Author-email: kurt.morgan@dv.net
Requires-Python: >=3.9,<4.0
Classifier: License :: OSI Approved :: MIT License
Classifier: Programming Language :: Python :: 3
Classifier: Programming Language :: Python :: 3.9
Classifier: Programming Language :: Python :: 3.10
Classifier: Programming Language :: Python :: 3.11
Classifier: Programming Language :: Python :: 3.12
Provides-Extra: async
Requires-Dist: aiohttp (>=3.9.5,<4.0.0) ; extra == "async"
Project-URL: Repository, https://github.com/dv-net/dv-python
